MANIFEST.in
README.md
pyproject.toml
setup.py
bin/nimcli
nbcli/__init__.py
nbcli/cli.py
nbcli/commands/__init__.py
nbcli/commands/list.py
nbcli/commands/misc.py
nbcli/commands/overview.py
nbcli/commands/register.py
nbcli/commands/stake.py
nbcli/commands/transfer.py
nbcli/commands/unstake.py
nbcli/commands/utils.py
nbcli/commands/wallets.py
nimcli.egg-info/PKG-INFO
nimcli.egg-info/SOURCES.txt
nimcli.egg-info/dependency_links.txt
nimcli.egg-info/requires.txt
nimcli.egg-info/top_level.txt
requirements/dev.txt
requirements/prod.txt
tests/__init__.py
tests/helpers/__init__.py
tests/helpers/helpers.py
tests/integration_tests/__init__.py
tests/integration_tests/test_cli.py
tests/integration_tests/test_cli_no_network.py